pysigma_backend_microsoft365defender/__init__.py
pysigma_backend_microsoft365defender-0.3.2.dist-info/LICENSE
pysigma_backend_microsoft365defender-0.3.2.dist-info/METADATA
pysigma_backend_microsoft365defender-0.3.2.dist-info/WHEEL
pysigma_backend_microsoft365defender-0.3.2.dist-info/RECORD
