Metadata-Version: 2.1
Name: pySigma-backend-microsoft365defender
Version: 0.3.2
Summary: This package has been renamed to pySigma-backend-kusto. Install pySigma-backend-kusto instead.
Home-page: https://github.com/AttackIQ/pySigma-backend-kusto
License: LGPL-3.0-only
Author: Stephen Lincoln
Author-email: stephen.lincoln@attackiq.com
Requires-Python: >=3.8,<4.0
Classifier: License :: OSI Approved :: GNU Lesser General Public License v3 (LGPLv3)
Classifier: Programming Language :: Python :: 3
Classifier: Programming Language :: Python :: 3.8
Classifier: Programming Language :: Python :: 3.9
Classifier: Programming Language :: Python :: 3.10
Classifier: Programming Language :: Python :: 3.11
Classifier: Programming Language :: Python :: 3.12
Requires-Dist: pySigma-backend-kusto (>=0.3.1)
Project-URL: Repository, https://github.com/AttackIQ/pySigma-backend-kusto
